grblogtools/__init__.py
grblogtools/__main__.py
grblogtools/api.py
grblogtools/cli.py
grblogtools/helpers.py
grblogtools/plotting.py
grblogtools/parameters/__init__.py
grblogtools/parameters/defaults.py
grblogtools/parameters/pretty.py
grblogtools/parameters/data/1000.json
grblogtools/parameters/data/1001.json
grblogtools/parameters/data/800.json
grblogtools/parameters/data/801.json
grblogtools/parameters/data/810.json
grblogtools/parameters/data/811.json
grblogtools/parameters/data/900.json
grblogtools/parameters/data/901.json
grblogtools/parameters/data/902.json
grblogtools/parameters/data/903.json
grblogtools/parameters/data/910.json
grblogtools/parameters/data/911.json
grblogtools/parameters/data/912.json
grblogtools/parameters/data/950.json
grblogtools/parameters/data/951.json
grblogtools/parameters/data/952.json
grblogtools/parameters/data/__init__.py
grblogtools/parameters/data/descriptions.json
grblogtools/parsers/__init__.py
grblogtools/parsers/barrier.py
grblogtools/parsers/continuous.py
grblogtools/parsers/header.py
grblogtools/parsers/nodelog.py
grblogtools/parsers/norel.py
grblogtools/parsers/presolve.py
grblogtools/parsers/simplex.py
grblogtools/parsers/single_log.py
grblogtools/parsers/termination.py
grblogtools/parsers/util.py
grblogtools-2.2.0.dist-info/LICENSE
grblogtools-2.2.0.dist-info/METADATA
grblogtools-2.2.0.dist-info/WHEEL
grblogtools-2.2.0.dist-info/top_level.txt
grblogtools-2.2.0.dist-info/RECORD
