Metadata-Version: 2.1
Name: grblogtools
Version: 2.2.0
Summary: Gurobi log file tools for parsing and exploring data
Home-page: https://github.com/Gurobi/grblogtools
Author: Gurobi Optimization, LLC
Author-email: support@gurobi.com
License: Apache-2.0
Platform: any
Classifier: License :: OSI Approved :: Apache Software License
Classifier: Operating System :: OS Independent
Classifier: Programming Language :: Python :: 3
Classifier: Programming Language :: Python :: 3 :: Only
Classifier: Programming Language :: Python :: 3.7
Classifier: Programming Language :: Python :: 3.8
Classifier: Programming Language :: Python :: 3.9
Classifier: Programming Language :: Python :: 3.10
Requires-Python: >=3.7
License-File: LICENSE
